{"trial_id": "02", "hyperparameters": {"space": [{"class_name": "Choice", "config": {"name": "sequence_length", "default": 5, "conditions": [], "values": [5, 10, 20], "ordered": true}}, {"class_name": "Int", "config": {"name": "units_lstm1", "default": null, "conditions": [], "min_value": 32, "max_value": 128, "step": 32, "sampling": "linear"}}, {"class_name": "Float", "config": {"name": "dropout1", "default": 0.1, "conditions": [], "min_value": 0.1, "max_value": 0.5, "step": 0.1, "sampling": "linear"}}, {"class_name": "Int", "config": {"name": "units_lstm2", "default": null, "conditions": [], "min_value": 16, "max_value": 64, "step": 16, "sampling": "linear"}}, {"class_name": "Float", "config": {"name": "dropout2", "default": 0.1, "conditions": [], "min_value": 0.1, "max_value": 0.5, "step": 0.1, "sampling": "linear"}}, {"class_name": "Float", "config": {"name": "learning_rate", "default": 0.0001, "conditions": [], "min_value": 0.0001, "max_value": 0.1, "step": null, "sampling": "log"}}], "values": {"sequence_length": 20, "units_lstm1": 64, "dropout1": 0.30000000000000004, "units_lstm2": 48, "dropout2": 0.2, "learning_rate": 0.0006273970174941373}}, "metrics": {"metrics": {"loss": {"direction": "min", "observations": [{"value": [0.00229653250426054], "step": 7}]}, "accuracy": {"direction": "max", "observations": [{"value": [0.9973099231719971], "step": 7}]}, "precision": {"direction": "min", "observations": [{"value": [0.9970171451568604], "step": 7}]}, "recall": {"direction": "min", "observations": [{"value": [0.9976043701171875], "step": 7}]}, "auc": {"direction": "min", "observations": [{"value": [0.999940037727356], "step": 7}]}, "val_loss": {"direction": "min", "observations": [{"value": [0.004983012098819017], "step": 7}]}, "val_accuracy": {"direction": "max", "observations": [{"value": [0.9946670532226562], "step": 7}]}, "val_precision": {"direction": "max", "observations": [{"value": [0.9108014106750488], "step": 7}]}, "val_recall": {"direction": "min", "observations": [{"value": [0.9191280007362366], "step": 7}]}, "val_auc": {"direction": "min", "observations": [{"value": [0.9979232549667358], "step": 7}]}}}, "score": 0.9108014106750488, "best_step": 7, "status": "COMPLETED", "message": null}